odoo/addons/l10n_es_vat_book_pos/README.rst
odoo/addons/l10n_es_vat_book_pos/__init__.py
odoo/addons/l10n_es_vat_book_pos/__manifest__.py
odoo/addons/l10n_es_vat_book_pos/i18n/l10n_es_vat_book_pos.pot
odoo/addons/l10n_es_vat_book_pos/models/__init__.py
odoo/addons/l10n_es_vat_book_pos/models/l10n_es_vat_book.py
odoo/addons/l10n_es_vat_book_pos/readme/CONTRIBUTORS.md
odoo/addons/l10n_es_vat_book_pos/readme/DESCRIPTION.md
odoo/addons/l10n_es_vat_book_pos/static/description/icon.png
odoo/addons/l10n_es_vat_book_pos/static/description/icon.svg
odoo/addons/l10n_es_vat_book_pos/static/description/index.html
odoo/addons/l10n_es_vat_book_pos/tests/__init__.py
odoo/addons/l10n_es_vat_book_pos/tests/test_vat_book_pos.py
odoo_addon_l10n_es_vat_book_pos-17.0.1.0.0.2.dist-info/METADATA
odoo_addon_l10n_es_vat_book_pos-17.0.1.0.0.2.dist-info/WHEEL
odoo_addon_l10n_es_vat_book_pos-17.0.1.0.0.2.dist-info/top_level.txt
odoo_addon_l10n_es_vat_book_pos-17.0.1.0.0.2.dist-info/RECORD
